{
    "version": 1,
    "all_bricks": {
        "1": {
            "submit_time": [
                1728348272
            ],
            "type": 4,
            "review_day": [
                1728403200,
                1728662400,
                1728921600,
                1729526400,
                1730736000,
                1733500800
            ]
        },
        "3": {
            "submit_time": [
                1730174277
            ],
            "type": 4,
            "review_day": [
                1730217600,
                1730476800,
                1730736000,
                1731340800,
                1732550400,
                1735315200
            ]
        },
        "11": {
            "submit_time": [
                1728437304
            ],
            "type": 4,
            "review_day": [
                1728489600,
                1728748800,
                1729008000,
                1729612800,
                1730822400,
                1733587200
            ]
        },
        "15": {
            "submit_time": [
                1728439831
            ],
            "type": 4,
            "review_day": [
                1728489600,
                1728748800,
                1729008000,
                1729612800,
                1730822400,
                1733587200
            ]
        },
        "42": {
            "submit_time": [
                1728525749,
                1728527984,
                1728528616
            ],
            "type": 4,
            "review_day": [
                1728576000,
                1728835200,
                1729094400,
                1729699200,
                1730908800,
                1733673600
            ]
        },
        "49": {
            "submit_time": [
                1728348985
            ],
            "type": 4,
            "review_day": [
                1728403200,
                1728662400,
                1728921600,
                1729526400,
                1730736000,
                1733500800
            ]
        },
        "76": {
            "submit_time": [
                1730344985,
                1730345006,
                1730345755,
                1730345771
            ],
            "type": 4,
            "review_day": [
                1730390400,
                1730649600,
                1730908800,
                1731513600,
                1732723200,
                1735488000
            ]
        },
        "128": {
            "submit_time": [
                1728350307
            ],
            "type": 4,
            "review_day": [
                1728403200,
                1728662400,
                1728921600,
                1729526400,
                1730736000,
                1733500800
            ]
        },
        "209": {
            "submit_time": [
                1730171073,
                1730171141,
                1730171320
            ],
            "type": 4,
            "review_day": [
                1730217600,
                1730476800,
                1730736000,
                1731340800,
                1732550400,
                1735315200
            ]
        },
        "283": {
            "submit_time": [
                1728436114
            ],
            "type": 4,
            "review_day": [
                1728489600,
                1728748800,
                1729008000,
                1729612800,
                1730822400,
                1733587200
            ]
        }
    }
}